COAL (CE-222)/lab 8/task1.v
`timescale 1ns / 1ps 

module task1 (
    output reg [31:0] out,
    input rd,wr,
    input [4:0] address,
    input [31:0] data,
    input clk
);
 reg [31:0] memory [31:0];

always @(posedge clk)
    begin   
        if(wr)
            memory[address]<=data;
        if(rd)
            out <= memory[address];
    end
            
endmodule

COAL (CE-222)/lab 8/test1.v
`timescale 1ns / 1ps
`include "task1.v"
module test1;
reg rd,wr;
reg [4:0] address;
reg clk;
reg [31:0] data;

wire [31:0] out;

    task1 uut(.out(out), .rd(rd), .wr(wr), 
    .address(address), .data(data), .clk(clk));
always #5 clk = ~clk;

    initial begin 
       
    clk = 0;
    rd = 0;
    wr = 0;
    address = 5'b00000;
    data = 33'h0;

    $dumpfile("test1.vcd");
    $dumpvars(0, test1);

    
    #20 rd = 0; wr = 1; address = 5'd0;  data = 33'd0;
    #20 rd = 0; wr = 1; address = 5'd1;  data = 33'd1;
    #20 rd = 0; wr = 1; address = 5'd2;  data = 33'd2;
    #20 rd = 0; wr = 1; address = 5'd3;  data = 33'd3;
    #20 rd = 0; wr = 1; address = 5'd4;  data = 33'd4;
    #20 rd = 0; wr = 1; address = 5'd5;  data = 33'd5;
    #20 rd = 0; wr = 1; address = 5'd6;  data = 33'd6;
    #20 rd = 0; wr = 1; address = 5'd7;  data = 33'd7;
    #20 rd = 0; wr = 1; address = 5'd8;  data = 33'd8;
    #20 rd = 0; wr = 1; address = 5'd9;  data = 33'd9;
    #20 rd = 0; wr = 1; address = 5'd10; data = 33'd10;
    #20 rd = 0; wr = 1; address = 5'd11; data = 33'd11;
    #20 rd = 0; wr = 1; address = 5'd12; data = 33'd12;
    #20 rd = 0; wr = 1; address = 5'd13; data = 33'd13;
    #20 rd = 0; wr = 1; address = 5'd14; data = 33'd14;
    #20 rd = 0; wr = 1; address = 5'd15; data = 33'd15;

    #40 wr = 0; 

    
    #20 rd = 1; wr = 0; address = 5'd0;
    #20 rd = 1; wr = 0; address = 5'd1;
    #20 rd = 1; wr = 0; address = 5'd2;
    #20 rd = 1; wr = 0; address = 5'd3;
    #20 rd = 1; wr = 0; address = 5'd4;
    #20 rd = 1; wr = 0; address = 5'd5;
    #20 rd = 1; wr = 0; address = 5'd6;
    #20 rd = 1; wr = 0; address = 5'd7;
    #20 rd = 1; wr = 0; address = 5'd8;
    #20 rd = 1; wr = 0; address = 5'd9;
    #20 rd = 1; wr = 0; address = 5'd10;
    #20 rd = 1; wr = 0; address = 5'd11;
    #20 rd = 1; wr = 0; address = 5'd12;
    #20 rd = 1; wr = 0; address = 5'd13;
    #20 rd = 1; wr = 0; address = 5'd14;
    #20 rd = 1; wr = 0; address = 5'd15;

    #40 $finish; 
end
    initial begin
        $monitor("Time: %0t | Addr: %d | DataIn: %d | Out: %d | WR: %b | RD: %b", 
                 $time, address, data, out, wr, rd);
    end
endmodule

COAL (CE-222)/lab 8/test1.vcd
$date
	Mon Apr 06 15:24:24 2026
$end
$version
	Icarus Verilog
$end
$timescale
	1ps
$end
$scope module test1 $end
$var wire 32 ! out [31:0] $end
$var reg 5 " address [4:0] $end
$var reg 1 # clk $end
$var reg 32 $ data [31:0] $end
$var reg 1 % rd $end
$var reg 1 & wr $end
$scope module uut $end
$var wire 5 ' address [4:0] $end
$var wire 1 # clk $end
$var wire 32 ( data [31:0] $end
$var wire 1 % rd $end
$var wire 1 & wr $end
$var reg 32 ) out [31:0] $end
$upscope $end
$upscope $end
$enddefinitions $end
#0
$dumpvars
bx )
b0 (
b0 '
0&
0%
b0 $
0#
b0 "
bx !
$end
#5000
1#
#10000
0#
#15000
1#
#20000
0#
1&
#25000
1#
#30000
0#
#35000
1#
#40000
0#
b1 $
b1 (
b1 "
b1 '
#45000
1#
#50000
0#
#55000
1#
#60000
0#
b10 $
b10 (
b10 "
b10 '
#65000
1#
#70000
0#
#75000
1#
#80000
0#
b11 $
b11 (
b11 "
b11 '
#85000
1#
#90000
0#
#95000
1#
#100000
0#
b100 $
b100 (
b100 "
b100 '
#105000
1#
#110000
0#
#115000
1#
#120000
0#
b101 $
b101 (
b101 "
b101 '
#125000
1#
#130000
0#
#135000
1#
#140000
0#
b110 $
b110 (
b110 "
b110 '
#145000
1#
#150000
0#
#155000
1#
#160000
0#
b111 $
b111 (
b111 "
b111 '
#165000
1#
#170000
0#
#175000
1#
#180000
0#
b1000 $
b1000 (
b1000 "
b1000 '
#185000
1#
#190000
0#
#195000
1#
#200000
0#
b1001 $
b1001 (
b1001 "
b1001 '
#205000
1#
#210000
0#
#215000
1#
#220000
0#
b1010 $
b1010 (
b1010 "
b1010 '
#225000
1#
#230000
0#
#235000
1#
#240000
0#
b1011 $
b1011 (
b1011 "
b1011 '
#245000
1#
#250000
0#
#255000
1#
#260000
0#
b1100 $
b1100 (
b1100 "
b1100 '
#265000
1#
#270000
0#
#275000
1#
#280000
0#
b1101 $
b1101 (
b1101 "
b1101 '
#285000
1#
#290000
0#
#295000
1#
#300000
0#
b1110 $
b1110 (
b1110 "
b1110 '
#305000
1#
#310000
0#
#315000
1#
#320000
0#
b1111 $
b1111 (
b1111 "
b1111 '
#325000
1#
#330000
0#
#335000
1#
#340000
0#
#345000
1#
#350000
0#
#355000
1#
#360000
0#
0&
#365000
1#
#370000
0#
#375000
1#
#380000
0#
b0 "
b0 '
1%
#385000
b0 !
b0 )
1#
#390000
0#
#395000
1#
#400000
0#
b1 "
b1 '
#405000
b1 !
b1 )
1#
#410000
0#
#415000
1#
#420000
0#
b10 "
b10 '
#425000
b10 !
b10 )
1#
#430000
0#
#435000
1#
#440000
0#
b11 "
b11 '
#445000
b11 !
b11 )
1#
#450000
0#
#455000
1#
#460000
0#
b100 "
b100 '
#465000
b100 !
b100 )
1#
#470000
0#
#475000
1#
#480000
0#
b101 "
b101 '
#485000
b101 !
b101 )
1#
#490000
0#
#495000
1#
#500000
0#
b110 "
b110 '
#505000
b110 !
b110 )
1#
#510000
0#
#515000
1#
#520000
0#
b111 "
b111 '
#525000
b111 !
b111 )
1#
#530000
0#
#535000
1#
#540000
0#
b1000 "
b1000 '
#545000
b1000 !
b1000 )
1#
#550000
0#
#555000
1#
#560000
0#
b1001 "
b1001 '
#565000
b1001 !
b1001 )
1#
#570000
0#
#575000
1#
#580000
0#
b1010 "
b1010 '
#585000
b1010 !
b1010 )
1#
#590000
0#
#595000
1#
#600000
0#
b1011 "
b1011 '
#605000
b1011 !
b1011 )
1#
#610000
0#
#615000
1#
#620000
0#
b1100 "
b1100 '
#625000
b1100 !
b1100 )
1#
#630000
0#
#635000
1#
#640000
0#
b1101 "
b1101 '
#645000
b1101 !
b1101 )
1#
#650000
0#
#655000
1#
#660000
0#
b1110 "
b1110 '
#665000
b1110 !
b1110 )
1#
#670000
0#
#675000
1#
#680000
0#
b1111 "
b1111 '
#685000
b1111 !
b1111 )
1#
