COAL (CE-222)/single_cycle_processor/mux.v
module mux2to1 (
    input   [31:0] in0,
    input   [31:0] in1,
    input          sel,
    output reg  [31:0] out
);

    always @(*) begin
        if (sel) begin
            out = in1;
        end else begin
            out = in0;
        end
    end

endmodule

COAL (CE-222)/single_cycle_processor/data_memory.v
module data_memory(
    input clk,
    input mem_read,
    input mem_write,
    input  wire [31:0] addr,
    input  wire [31:0] write_data,
    output reg  [31:0] read_data
);

    reg [31:0] mem [0:255];
    integer i;

    initial begin
        for (i = 0; i < 256; i = i + 1)
            mem[i] = 32'b0;
            
        mem[0] = 32'd10; // Value at addr 0
        mem[1] = 32'd20; // Value at addr 4 (index 1)
    end

    always @(*) begin
        if (mem_read) begin
            read_data = mem[addr[9:2]];
        end else begin
            read_data = 32'b0;
        end
    end

    always @(posedge clk) begin
        if (mem_write)
            mem[addr[9:2]] <= write_data;
    end

endmodule

COAL (CE-222)/single_cycle_processor/alu.v
module alu(
    input  wire [31:0] a,
    input  wire [31:0] b,
    input  wire [3:0]  alu_ctrl,
    output reg  [31:0] result,
    output wire        zero
);

    always @(*) begin
        case (alu_ctrl)
            4'b0000: result = a & b; // AND
            4'b0001: result = a ^ b; // XOR
            4'b0010: result = a + b; // ADD
            4'b0011: result = a | b; // OR
            4'b0110: result = a - b; // SUB
            4'b1010: result = b; // LUI
            default: result = 32'd0;
        endcase
    end

    assign zero = (result == 32'd0);

endmodule

COAL (CE-222)/single_cycle_processor/alu_control.v
module alu_control(
    input  wire [1:0] alu_op,
    input  wire [2:0] funct3,
    input  wire [6:0] funct7,
    output reg  [3:0] alu_ctrl
);

    always @(*) begin
        case (alu_op)
            2'b00: alu_ctrl = 4'b0010; // lw/sw
            2'b01: alu_ctrl = 4'b0110; // beq
            2'b10: begin    //R-type
                case (funct3)
                    3'b000: begin // add/sub
                        if (funct7[5])
                            alu_ctrl = 4'b0110; // sub
                        else
                            alu_ctrl = 4'b0010; // add
                    end
                    3'b110: alu_ctrl = 4'b0011; // or
                    3'b111: alu_ctrl = 4'b0000; // and
                    default: alu_ctrl = 4'b0010;
                endcase
            end
            default: alu_ctrl = 4'b0010;
        endcase
    end

endmodule

COAL (CE-222)/single_cycle_processor/adder.v
module adder(
    input  wire [31:0] a,
    input  wire [31:0] b,
    output wire [31:0] sum
);

    assign sum = a + b;

endmodule

COAL (CE-222)/single_cycle_processor/register_file.v
module register_file(
    input  wire        clk,
    input  wire        reset,
    input  wire        reg_write,
    input  wire [4:0]  read_reg1,
    input  wire [4:0]  read_reg2,
    input  wire [4:0]  write_reg,
    input  wire [31:0] write_data,
    output wire [31:0] read_data1,
    output wire [31:0] read_data2
);

    reg [31:0] registers [0:31];
    integer i;

    always @(posedge clk or posedge reset) begin
        if (reset) begin
            for (i = 0; i < 32; i = i + 1)
                registers[i] <= 32'b0;
        end else begin
            if (reg_write && (write_reg != 5'b00000))
                registers[write_reg] <= write_data;

            registers[0] <= 32'b0;
        end
    end

    assign read_data1 = registers[read_reg1];
    assign read_data2 = registers[read_reg2];

endmodule

COAL (CE-222)/single_cycle_processor/control_unit.v
module control_unit(
    input  wire [6:0] opcode,
    output reg       alu_src,
    output reg       mem_to_reg,
    output reg       reg_write,
    output reg       mem_read,
    output reg       mem_write,
    output reg       branch,
    output reg [1:0] alu_op
);

    always @(*) begin
        alu_src    = 1'b0;
        mem_to_reg = 1'b0;
        reg_write  = 1'b0;
        mem_read   = 1'b0;
        mem_write  = 1'b0;
        branch     = 1'b0;
        alu_op     = 2'b00;

        case (opcode)
            7'b0110011: begin // R-type
                reg_write = 1'b1;
                alu_op    = 2'b10;
            end
            7'b0000011: begin // Load (lw)
                alu_src    = 1'b1;
                mem_read   = 1'b1;
                mem_to_reg = 1'b1;
                reg_write  = 1'b1;
                alu_op     = 2'b00;
            end
            7'b0100011: begin // Store (sw)
                alu_src    = 1'b1;
                mem_write  = 1'b1;
                alu_op     = 2'b00;
            end
            7'b1100011: begin // Branch (beq)
                branch = 1'b1;
                alu_op = 2'b01;
            end
            default: begin
            end
        endcase
    end

endmodule

COAL (CE-222)/single_cycle_processor/immediate_generator.v
module immediate_generator(
    input  wire [31:0] instruction,
    output reg  [31:0] imm
);

    wire [6:0] opcode = instruction[6:0];

    always @(*) begin
        case (opcode)
            7'b0000011: imm = {{20{instruction[31]}}, instruction[31:20]}; // I-type (lw)
            7'b0100011: imm = {{20{instruction[31]}}, instruction[31:25], instruction[11:7]}; // S-type (sw)
            7'b1100011: imm = {{19{instruction[31]}}, instruction[31], instruction[7], instruction[30:25], instruction[11:8], 1'b0}; // B-type (beq)
            default:    imm = 32'b0;
        endcase
    end

endmodule

COAL (CE-222)/single_cycle_processor/instruction_memory.v
`timescale 1ns / 1ps

module instruction_decoder(
    input  wire [31:0] instruction,
    output wire [6:0]  opcode,
    output wire [4:0]  rd,
    output wire [2:0]  funct3,
    output wire [4:0]  rs1,
    output wire [4:0]  rs2,
    output wire [6:0]  funct7,
    output wire [31:0] immediate
);

    assign opcode = instruction[6:0];
    assign rd = instruction[11:7];
    assign funct3 = instruction[14:12];
    assign rs1 = instruction[19:15];
    assign rs2 = instruction[24:20];
    assign funct7 = instruction[31:25];

    immediate_generator imm_gen(
        .instruction(instruction),
        .imm(immediate)
    );

endmodule

module instruction_memory(
    input  wire [31:0] addr,
    input  wire        reset,
    output wire [31:0] instruction,
    output wire [6:0]  opcode,
    output wire [4:0]  rd,
    output wire [2:0]  funct3,
    output wire [4:0]  rs1,
    output wire [4:0]  rs2,
    output wire [6:0]  funct7,
    output wire [31:0] immediate
);

    reg [7:0] memory [0:63];
    integer i;

    assign instruction = {memory[addr + 32'd3], memory[addr + 32'd2], memory[addr + 32'd1], memory[addr]};

    instruction_decoder decoder(
        .instruction(instruction),
        .opcode(opcode),
        .rd(rd),
        .funct3(funct3),
        .rs1(rs1),
        .rs2(rs2),
        .funct7(funct7),
        .immediate(immediate)
    );

    initial begin
        for (i = 0; i < 64; i = i + 1)
            memory[i] = 8'b00000000;

        // 0: lw x1, 0(x0)     (x1 = 10)
        memory[0]  = 8'b10000011; memory[1] = 8'b00100000; memory[2] = 8'b00000000; memory[3] = 8'b00000000;
        
        // 4: lw x2, 4(x0)     (x2 = 20)
        memory[4]  = 8'b00000011; memory[5] = 8'b00100001; memory[6] = 8'b01000000; memory[7] = 8'b00000000;
        
        // 8: add x3, x1, x2   (x3 = 30)
        memory[8]  = 8'b10110011; memory[9] = 8'b10000001; memory[10] = 8'b00100000; memory[11] = 8'b00000000;
        
        // 12: sub x4, x2, x1  (x4 = 10)
        memory[12] = 8'b00110011; memory[13] = 8'b00000010; memory[14] = 8'b00010001; memory[15] = 8'b01000000;
        
        // 16: sw x3, 8(x0)    (mem[8] = 30)
        memory[16] = 8'b00100011; memory[17] = 8'b00100100; memory[18] = 8'b00110000; memory[19] = 8'b00000000;
        
        // 20: and x5, x3, x4  (x5 = 30 & 10 = 10)
        memory[20] = 8'b10110011; memory[21] = 8'b11110010; memory[22] = 8'b01000001; memory[23] = 8'b00000000;
        
        // 24: or x6, x3, x4   (x6 = 30 | 10 = 30)
        memory[24] = 8'b00110011; memory[25] = 8'b11100011; memory[26] = 8'b01000001; memory[27] = 8'b00000000;
        
        // 28: beq x4, x1, 8   (if 10 == 10, jump to 36)
        memory[28] = 8'b01100011; memory[29] = 8'b00000100; memory[30] = 8'b00010010; memory[31] = 8'b00000000;
        
        // 32: sw x1, 12(x0)   (skipped)
        memory[32] = 8'b00100011; memory[33] = 8'b00100110; memory[34] = 8'b00010000; memory[35] = 8'b00000000;
        
        // 36: sw x2, 16(x0)   (mem[16] = 20)
        memory[36] = 8'b00100011; memory[37] = 8'b00101000; memory[38] = 8'b00100000; memory[39] = 8'b00000000;
    end

endmodule

/*
    TEST PROGRAM:
    0:  lw  x1, 0(x0)   # x1 = 10 (from pre-loaded memory)
    4:  lw  x2, 4(x0)   # x2 = 20 (from pre-loaded memory)
    8:  add x3, x1, x2  # x3 = 30
    12: sub x4, x2, x1  # x4 = 10
    16: sw  x3, 8(x0)   # mem[8] = 30
    20: and x5, x3, x4  # x5 = 10
    24: or  x6, x3, x4  # x6 = 30
    28: beq x4, x1, 8   # if x4(10) == x1(10), jump to 36 (offset 8)
    32: sw  x1, 12(x0)  # SHOULD BE SKIPPED
    36: sw  x2, 16(x0)  # mem[16] = 20
*/

COAL (CE-222)/single_cycle_processor/program_counter.v
module program_counter(
    input  wire        clk,
    input  wire        reset,
    input  wire [31:0] next_pc,
    output reg  [31:0] pc_out
);

    always @(posedge clk or posedge reset) begin
        if (reset)
            pc_out <= 32'b0;
        else
            pc_out <= next_pc;
    end

endmodule

COAL (CE-222)/single_cycle_processor/single_cycle_processor.v
module single_cycle_processor(
    input          clk,
    input          reset,
    output  [31:0] pc_out,
    output  [31:0] instruction,
    output  [31:0] alu_result,
    output  [31:0] read_data,
    output         zero_flag,
    output  [4:0]  rs1,
    output  [4:0]  rs2,
    output  [4:0]  rd
);

    wire [31:0] pc_next;
    wire [31:0] pc_plus_4;
    wire [31:0] branch_target;
    wire [31:0] imm;
    wire [6:0]  opcode;
    wire [2:0]  funct3;
    wire [6:0]  funct7;
    wire [31:0] alu_input_b;
    wire [31:0] write_back_data;
    wire [31:0] read_data1;
    wire [31:0] read_data2;
    wire [3:0]  alu_ctrl;
    wire        alu_src;
    wire        mem_to_reg;
    wire        reg_write;
    wire        mem_read;
    wire        mem_write;
    wire        branch;
    wire [1:0]  alu_op;
    wire        branch_taken;

    program_counter pc(
        .clk(clk),
        .reset(reset),
        .next_pc(pc_next),
        .pc_out(pc_out)
    );

    instruction_memory imem(
        .addr(pc_out),
        .reset(reset),
        .instruction(instruction),
        .opcode(opcode),
        .rd(rd),
        .funct3(funct3),
        .rs1(rs1),
        .rs2(rs2),
        .funct7(funct7),
        .immediate(imm)
    );

    adder pc_adder(
        .a(pc_out),
        .b(32'd4),
        .sum(pc_plus_4)
    );

    control_unit ctrl(
        .opcode(opcode),
        .alu_src(alu_src),
        .mem_to_reg(mem_to_reg),
        .reg_write(reg_write),
        .mem_read(mem_read),
        .mem_write(mem_write),
        .branch(branch),
        .alu_op(alu_op)
    );

    register_file regs(
        .clk(clk),
        .reset(reset),
        .reg_write(reg_write),
        .read_reg1(rs1),
        .read_reg2(rs2),
        .write_reg(rd),
        .write_data(write_back_data),
        .read_data1(read_data1),
        .read_data2(read_data2)
    );

    adder target_adder(
        .a(pc_out),
        .b(imm),
        .sum(branch_target)
    );

    assign branch_taken = branch & zero_flag;

    mux2to1 branch_mux(
        .in0(pc_plus_4),
        .in1(branch_target),
        .sel(branch_taken),
        .out(pc_next)
    );

    mux2to1 alu_src_mux(
        .in0(read_data2),
        .in1(imm),
        .sel(alu_src),
        .out(alu_input_b)
    );

    alu_control aluctrl(
        .alu_op(alu_op),
        .funct3(funct3),
        .funct7(funct7),
        .alu_ctrl(alu_ctrl)
    );

    alu main_alu(
        .a(read_data1),
        .b(alu_input_b),
        .alu_ctrl(alu_ctrl),
        .result(alu_result),
        .zero(zero_flag)
    );

    data_memory dmem(
        .clk(clk),
        .mem_read(mem_read),
        .mem_write(mem_write),
        .addr(alu_result),
        .write_data(read_data2),
        .read_data(read_data)
    );

    mux2to1 mem_to_reg_mux(
        .in0(alu_result),
        .in1(read_data),
        .sel(mem_to_reg),
        .out(write_back_data)
    );

endmodule

COAL (CE-222)/single_cycle_processor/single_cycle_processor_tb.v
`timescale 1ns / 1ps

module single_cycle_processor_tb;

    reg clk;
    reg reset;

    wire [31:0] pc_out;
    wire [31:0] instruction;
    wire [31:0] alu_result;
    wire [31:0] read_data;
    wire        zero_flag;
    wire [4:0]  rs1;
    wire [4:0]  rs2;
    wire [4:0]  rd;

    single_cycle_processor uut (
        .clk(clk),
        .reset(reset),
        .pc_out(pc_out),
        .instruction(instruction),
        .alu_result(alu_result),
        .read_data(read_data),
        .zero_flag(zero_flag),
        .rs1(rs1),
        .rs2(rs2),
        .rd(rd)
    );

    initial begin
        $dumpfile("single_cycle_processor.vcd");
        $dumpvars(0, single_cycle_processor_tb);
    end

    initial begin
        clk = 1'b0;
        forever #5 clk = ~clk;
    end

    initial begin
        reset = 1'b1;
        #12;
        reset = 1'b0;

        #150;

        $display("\n[FINAL REGISTER VALUES]");
        $display("x1: %d (Expected: 10)", uut.regs.registers[1]);
        $display("x2: %d (Expected: 20)", uut.regs.registers[2]);
        $display("x3: %d (Expected: 30)", uut.regs.registers[3]);
        $display("x4: %d (Expected: 10)", uut.regs.registers[4]);
        $display("x5: %d (Expected: 10)", uut.regs.registers[5]);
        $display("x6: %d (Expected: 30)", uut.regs.registers[6]);

        $display("\n[FINAL DATA MEMORY VALUES]");
        $display("mem[8] : %d (Expected: 30)", uut.dmem.mem[2]);
        $display("mem[12]: %d (Expected: 0)",  uut.dmem.mem[3]);
        $display("mem[16]: %d (Expected: 20)", uut.dmem.mem[4]);
        
        $display("\nSIMULATION COMPLETE\n");

        $finish;
    end

    // --- Instruction Decoder for Simulation Trace ---
    reg [255:0] mnemonic;
    always @(instruction) begin
        case (instruction[6:0])
            7'b0000011: mnemonic = "lw";
            7'b0100011: mnemonic = "sw";
            7'b1100011: mnemonic = "beq";
            7'b0110011: begin
                case (instruction[14:12])
                    3'b000: mnemonic = (instruction[31:25] == 7'h20) ? "sub" : "add";
                    3'b111: mnemonic = "and";
                    3'b110: mnemonic = "or";
                    default: mnemonic = "unknown";
                endcase
            end
            default: mnemonic = "nop/unknown";
        endcase
    end

    initial begin
        $display("\n[SIMULATION TRACE]");
        $display("-------------------------------------------------------------------------");
        $display(" Time |  PC  | Instruction | Mnemonic | rs1 | rs2 |  rd | ALU Out | Zero");
        $display("-------------------------------------------------------------------------");
        forever begin
            @(negedge clk);
            if (instruction != 32'h0 && instruction !== 32'hx) begin
                $display(" %4t |  %h |  %h |   %-5s  |  %2d |  %2d |  %2d | %h |  %b", 
                         $time, pc_out, instruction, mnemonic, rs1, rs2, rd, alu_result, zero_flag);
            end
        end
    end

endmodule

COAL (CE-222)/single_cycle_processor/single_cycle_processor.vcd
$date
	Fri May 08 10:41:06 2026
$end
$version
	Icarus Verilog
$end
$timescale
	1ps
$end
$scope module single_cycle_processor_tb $end
$var wire 1 ! zero_flag $end
$var wire 5 " rs2 [4:0] $end
$var wire 5 # rs1 [4:0] $end
$var wire 32 $ read_data [31:0] $end
$var wire 5 % rd [4:0] $end
$var wire 32 & pc_out [31:0] $end
$var wire 32 ' instruction [31:0] $end
$var wire 32 ( alu_result [31:0] $end
$var reg 1 ) clk $end
$var reg 256 * mnemonic [255:0] $end
$var reg 1 + reset $end
$scope module uut $end
$var wire 1 , branch_taken $end
$var wire 1 ) clk $end
$var wire 1 + reset $end
$var wire 1 ! zero_flag $end
$var wire 32 - write_back_data [31:0] $end
$var wire 5 . rs2 [4:0] $end
$var wire 5 / rs1 [4:0] $end
$var wire 1 0 reg_write $end
$var wire 32 1 read_data2 [31:0] $end
$var wire 32 2 read_data1 [31:0] $end
$var wire 32 3 read_data [31:0] $end
$var wire 5 4 rd [4:0] $end
$var wire 32 5 pc_plus_4 [31:0] $end
$var wire 32 6 pc_out [31:0] $end
$var wire 32 7 pc_next [31:0] $end
$var wire 7 8 opcode [6:0] $end
$var wire 1 9 mem_write $end
$var wire 1 : mem_to_reg $end
$var wire 1 ; mem_read $end
$var wire 32 < instruction [31:0] $end
$var wire 32 = imm [31:0] $end
$var wire 7 > funct7 [6:0] $end
$var wire 3 ? funct3 [2:0] $end
$var wire 32 @ branch_target [31:0] $end
$var wire 1 A branch $end
$var wire 1 B alu_src $end
$var wire 32 C alu_result [31:0] $end
$var wire 2 D alu_op [1:0] $end
$var wire 32 E alu_input_b [31:0] $end
$var wire 4 F alu_ctrl [3:0] $end
$scope module alu_src_mux $end
$var wire 1 B sel $end
$var wire 32 G in1 [31:0] $end
$var wire 32 H in0 [31:0] $end
$var reg 32 I out [31:0] $end
$upscope $end
$scope module aluctrl $end
$var wire 7 J funct7 [6:0] $end
$var wire 3 K funct3 [2:0] $end
$var wire 2 L alu_op [1:0] $end
$var reg 4 M alu_ctrl [3:0] $end
$upscope $end
$scope module branch_mux $end
$var wire 1 , sel $end
$var wire 32 N in1 [31:0] $end
$var wire 32 O in0 [31:0] $end
$var reg 32 P out [31:0] $end
$upscope $end
$scope module ctrl $end
$var wire 7 Q opcode [6:0] $end
$var reg 2 R alu_op [1:0] $end
$var reg 1 B alu_src $end
$var reg 1 A branch $end
$var reg 1 ; mem_read $end
$var reg 1 : mem_to_reg $end
$var reg 1 9 mem_write $end
$var reg 1 0 reg_write $end
$upscope $end
$scope module dmem $end
$var wire 1 ) clk $end
$var wire 1 ; mem_read $end
$var wire 1 9 mem_write $end
$var wire 32 S write_data [31:0] $end
$var wire 32 T addr [31:0] $end
$var reg 32 U read_data [31:0] $end
$var integer 32 V i [31:0] $end
$upscope $end
$scope module imem $end
$var wire 1 + reset $end
$var wire 5 W rs2 [4:0] $end
$var wire 5 X rs1 [4:0] $end
$var wire 5 Y rd [4:0] $end
$var wire 7 Z opcode [6:0] $end
$var wire 32 [ instruction [31:0] $end
$var wire 32 \ immediate [31:0] $end
$var wire 7 ] funct7 [6:0] $end
$var wire 3 ^ funct3 [2:0] $end
$var wire 32 _ addr [31:0] $end
$var integer 32 ` i [31:0] $end
$scope module decoder $end
$var wire 32 a instruction [31:0] $end
$var wire 5 b rs2 [4:0] $end
$var wire 5 c rs1 [4:0] $end
$var wire 5 d rd [4:0] $end
$var wire 7 e opcode [6:0] $end
$var wire 32 f immediate [31:0] $end
$var wire 7 g funct7 [6:0] $end
$var wire 3 h funct3 [2:0] $end
$scope module imm_gen $end
$var wire 32 i instruction [31:0] $end
$var wire 7 j opcode [6:0] $end
$var reg 32 k imm [31:0] $end
$upscope $end
$upscope $end
$scope task load_program $end
$upscope $end
$upscope $end
$scope module main_alu $end
$var wire 4 l alu_ctrl [3:0] $end
$var wire 32 m b [31:0] $end
$var wire 32 n a [31:0] $end
$var reg 32 o result [31:0] $end
$var reg 1 ! zero $end
$upscope $end
$scope module mem_to_reg_mux $end
$var wire 32 p in0 [31:0] $end
$var wire 32 q in1 [31:0] $end
$var wire 1 : sel $end
$var reg 32 r out [31:0] $end
$upscope $end
$scope module pc $end
$var wire 1 ) clk $end
$var wire 32 s next_pc [31:0] $end
$var wire 1 + reset $end
$var reg 32 t pc_out [31:0] $end
$upscope $end
$scope module pc_adder $end
$var wire 32 u a [31:0] $end
$var wire 32 v b [31:0] $end
$var wire 32 w sum [31:0] $end
$upscope $end
$scope module regs $end
$var wire 1 ) clk $end
$var wire 32 x read_data1 [31:0] $end
$var wire 32 y read_data2 [31:0] $end
$var wire 5 z read_reg1 [4:0] $end
$var wire 5 { read_reg2 [4:0] $end
$var wire 1 0 reg_write $end
$var wire 1 + reset $end
$var wire 32 | write_data [31:0] $end
$var wire 5 } write_reg [4:0] $end
$var integer 32 ~ i [31:0] $end
$upscope $end
$scope module target_adder $end
$var wire 32 !" a [31:0] $end
$var wire 32 "" b [31:0] $end
$var wire 32 #" sum [31:0] $end
$upscope $end
$upscope $end
$upscope $end
$enddefinitions $end
#0
$dumpvars
b0 #"
b0 ""
b0 !"
b100000 ~
b1 }
b1010 |
b0 {
b0 z
b0 y
b0 x
b100 w
b100 v
b0 u
b0 t
b100 s
b1010 r
b1010 q
b0 p
b0 o
b0 n
b0 m
b10 l
b0 k
b11 j
b10000010000011 i
b10 h
b0 g
b0 f
b11 e
b1 d
b0 c
b0 b
b10000010000011 a
b1000000 `
b0 _
b10 ^
b0 ]
b0 \
b10000010000011 [
b11 Z
b1 Y
b0 X
b0 W
b100000000 V
b1010 U
b0 T
b0 S
b0 R
b11 Q
b100 P
b100 O
b0 N
b10 M
b0 L
b10 K
b0 J
b0 I
b0 H
b0 G
b10 F
b0 E
b0 D
b0 C
1B
0A
b0 @
b10 ?
b0 >
b0 =
b10000010000011 <
1;
1:
09
b11 8
b100 7
b0 6
b100 5
b1 4
b1010 3
b0 2
b0 1
10
b0 /
b0 .
b1010 -
0,
1+
b110110001110111 *
0)
b0 (
b10000010000011 '
b0 &
b1 %
b1010 $
b0 #
b0 "
1!
$end
#5000
b100000 ~
1)
#10000
0)
#12000
0+
#15000
b10100 -
b10100 r
b10100 |
b10100 $
b10100 3
b10100 U
b10100 q
0!
b100 (
b100 C
b100 T
b100 o
b100 p
b100 E
b100 I
b100 m
b1000 7
b1000 P
b1000 s
b10 %
b10 4
b10 Y
b10 d
b10 }
b100 "
b100 .
b100 W
b100 b
b100 {
b100 =
b100 G
b100 \
b100 f
b100 k
b100 ""
b1000 5
b1000 O
b1000 w
b1000 @
b1000 N
b1000 #"
b10000000010000100000011 '
b10000000010000100000011 <
b10000000010000100000011 [
b10000000010000100000011 a
b10000000010000100000011 i
b100 &
b100 6
b100 _
b100 t
b100 u
b100 !"
1)
#20000
0)
#25000
b0 $
b0 3
b0 U
b0 q
b11110 -
b11110 r
b11110 |
b10 D
b10 L
b10 R
0;
10
0:
0B
b11110 (
b11110 C
b11110 T
b11110 o
b11110 p
b10100 E
b10100 I
b10100 m
b1100 7
b1100 P
b1100 s
b110011 8
b110011 Q
b110011 Z
b110011 e
b11 %
b11 4
b11 Y
b11 d
b11 }
b110011 j
b0 ?
b0 K
b0 ^
b0 h
b1010 2
b1010 n
b1010 x
b1 #
b1 /
b1 X
b1 c
b1 z
b10100 1
b10100 H
b10100 S
b10100 y
b10 "
b10 .
b10 W
b10 b
b10 {
b0 =
b0 G
b0 \
b0 f
b0 k
b0 ""
b11000010110010001100100 *
b1100 5
b1100 O
b1100 w
b1000 @
b1000 N
b1000 #"
b1000001000000110110011 '
b1000001000000110110011 <
b1000001000000110110011 [
b1000001000000110110011 a
b1000001000000110110011 i
b1000 &
b1000 6
b1000 _
b1000 t
b1000 u
b1000 !"
1)
#30000
0)
#35000
b1010 -
b1010 r
b1010 |
b1010 (
b1010 C
b1010 T
b1010 o
b1010 p
b1010 E
b1010 I
b1010 m
b110 F
b110 M
b110 l
b10000 7
b10000 P
b10000 s
b100 %
b100 4
b100 Y
b100 d
b100 }
b10100 2
b10100 n
b10100 x
b10 #
b10 /
b10 X
b10 c
b10 z
b1010 1
b1010 H
b1010 S
b1010 y
b1 "
b1 .
b1 W
b1 b
b1 {
b100000 >
b100000 J
b100000 ]
b100000 g
b11100110111010101100010 *
b10000 5
b10000 O
b10000 w
b1100 @
b1100 N
b1100 #"
b1000000000100010000001000110011 '
b1000000000100010000001000110011 <
b1000000000100010000001000110011 [
b1000000000100010000001000110011 a
b1000000000100010000001000110011 i
b1100 &
b1100 6
b1100 _
b1100 t
b1100 u
b1100 !"
1)
#40000
0)
#45000
b1000 -
b1000 r
b1000 |
19
1B
b0 D
b0 L
b0 R
00
b1000 =
b1000 G
b1000 \
b1000 f
b1000 k
b1000 ""
b1000 (
b1000 C
b1000 T
b1000 o
b1000 p
b1000 E
b1000 I
b1000 m
b10 F
b10 M
b10 l
b10100 7
b10100 P
b10100 s
b100011 8
b100011 Q
b100011 Z
b100011 e
b100011 j
b1000 %
b1000 4
b1000 Y
b1000 d
b1000 }
b10 ?
b10 K
b10 ^
b10 h
b0 2
b0 n
b0 x
b0 #
b0 /
b0 X
b0 c
b0 z
b11110 1
b11110 H
b11110 S
b11110 y
b11 "
b11 .
b11 W
b11 b
b11 {
b0 >
b0 J
b0 ]
b0 g
b111001101110111 *
b10100 5
b10100 O
b10100 w
b11000 @
b11000 N
b11000 #"
b1100000010010000100011 '
b1100000010010000100011 <
b1100000010010000100011 [
b1100000010010000100011 a
b1100000010010000100011 i
b10000 &
b10000 6
b10000 _
b10000 t
b10000 u
b10000 !"
1)
#50000
0)
#55000
b0 F
b0 M
b0 l
b1010 -
b1010 r
b1010 |
b10 D
b10 L
b10 R
10
09
0B
b1010 (
b1010 C
b1010 T
b1010 o
b1010 p
b1010 E
b1010 I
b1010 m
b11000 7
b11000 P
b11000 s
b110011 8
b110011 Q
b110011 Z
b110011 e
b110011 j
b101 %
b101 4
b101 Y
b101 d
b101 }
b111 ?
b111 K
b111 ^
b111 h
b11110 2
b11110 n
b11110 x
b11 #
b11 /
b11 X
b11 c
b11 z
b1010 1
b1010 H
b1010 S
b1010 y
b100 "
b100 .
b100 W
b100 b
b100 {
b0 =
b0 G
b0 \
b0 f
b0 k
b0 ""
b11000010110111001100100 *
b11000 5
b11000 O
b11000 w
b10100 @
b10100 N
b10100 #"
b10000011111001010110011 '
b10000011111001010110011 <
b10000011111001010110011 [
b10000011111001010110011 a
b10000011111001010110011 i
b10100 &
b10100 6
b10100 _
b10100 t
b10100 u
b10100 !"
1)
#60000
0)
#65000
b11110 -
b11110 r
b11110 |
b11110 (
b11110 C
b11110 T
b11110 o
b11110 p
b11 F
b11 M
b11 l
b11100 7
b11100 P
b11100 s
b110 %
b110 4
b110 Y
b110 d
b110 }
b110 ?
b110 K
b110 ^
b110 h
b110111101110010 *
b11100 5
b11100 O
b11100 w
b11000 @
b11000 N
b11000 #"
b10000011110001100110011 '
b10000011110001100110011 <
b10000011110001100110011 [
b10000011110001100110011 a
b10000011110001100110011 i
b11000 &
b11000 6
b11000 _
b11000 t
b11000 u
b11000 !"
1)
#70000
0)
#75000
1,
1!
b0 -
b0 r
b0 |
1A
b1 D
b1 L
b1 R
00
b1000 =
b1000 G
b1000 \
b1000 f
b1000 k
b1000 ""
b110 F
b110 M
b110 l
b0 (
b0 C
b0 T
b0 o
b0 p
b100100 7
b100100 P
b100100 s
b1100011 8
b1100011 Q
b1100011 Z
b1100011 e
b1100011 j
b1000 %
b1000 4
b1000 Y
b1000 d
b1000 }
b0 ?
b0 K
b0 ^
b0 h
b1010 2
b1010 n
b1010 x
b100 #
b100 /
b100 X
b100 c
b100 z
b1 "
b1 .
b1 W
b1 b
b1 {
b11000100110010101110001 *
b100000 5
b100000 O
b100000 w
b100100 @
b100100 N
b100100 #"
b100100000010001100011 '
b100100000010001100011 <
b100100000010001100011 [
b100100000010001100011 a
b100100000010001100011 i
b11100 &
b11100 6
b11100 _
b11100 t
b11100 u
b11100 !"
1)
#80000
0)
#85000
b10 F
b10 M
b10 l
0,
b10000 -
b10000 r
b10000 |
19
1B
b0 D
b0 L
b0 R
0A
0!
b10000 (
b10000 C
b10000 T
b10000 o
b10000 p
b10000 E
b10000 I
b10000 m
b101000 7
b101000 P
b101000 s
b100011 8
b100011 Q
b100011 Z
b100011 e
b100011 j
b10000 %
b10000 4
b10000 Y
b10000 d
b10000 }
b10 ?
b10 K
b10 ^
b10 h
b0 2
b0 n
b0 x
b0 #
b0 /
b0 X
b0 c
b0 z
b10100 1
b10100 H
b10100 S
b10100 y
b10 "
b10 .
b10 W
b10 b
b10 {
b10000 =
b10000 G
b10000 \
b10000 f
b10000 k
b10000 ""
b111001101110111 *
b101000 5
b101000 O
b101000 w
b110100 @
b110100 N
b110100 #"
b1000000010100000100011 '
b1000000010100000100011 <
b1000000010100000100011 [
b1000000010100000100011 a
b1000000010100000100011 i
b100100 &
b100100 6
b100100 _
b100100 t
b100100 u
b100100 !"
1)
#90000
0)
#95000
b0 -
b0 r
b0 |
1!
b0 (
b0 C
b0 T
b0 o
b0 p
09
0B
b0 E
b0 I
b0 m
b101100 7
b101100 P
b101100 s
b0 8
b0 Q
b0 Z
b0 e
b0 j
b0 %
b0 4
b0 Y
b0 d
b0 }
b0 ?
b0 K
b0 ^
b0 h
b0 1
b0 H
b0 S
b0 y
b0 "
b0 .
b0 W
b0 b
b0 {
b0 =
b0 G
b0 \
b0 f
b0 k
b0 ""
b110111001101111011100000010111101110101011011100110101101101110011011110111011101101110 *
b101100 5
b101100 O
b101100 w
b101000 @
b101000 N
b101000 #"
b0 '
b0 <
b0 [
b0 a
b0 i
b101000 &
b101000 6
b101000 _
b101000 t
b101000 u
b101000 !"
1)
#100000
0)
#105000
b110000 7
b110000 P
b110000 s
b110000 5
b110000 O
b110000 w
b101100 @
b101100 N
b101100 #"
b101100 &
b101100 6
b101100 _
b101100 t
b101100 u
b101100 !"
1)
#110000
0)
#115000
b110100 7
b110100 P
b110100 s
b110100 5
b110100 O
b110100 w
b110000 @
b110000 N
b110000 #"
b110000 &
b110000 6
b110000 _
b110000 t
b110000 u
b110000 !"
1)
#120000
0)
#125000
b111000 7
b111000 P
b111000 s
b111000 5
b111000 O
b111000 w
b110100 @
b110100 N
b110100 #"
b110100 &
b110100 6
b110100 _
b110100 t
b110100 u
b110100 !"
1)
#130000
0)
#135000
b111100 7
b111100 P
b111100 s
b111100 5
b111100 O
b111100 w
b111000 @
b111000 N
b111000 #"
b111000 &
b111000 6
b111000 _
b111000 t
b111000 u
b111000 !"
1)
#140000
0)
#145000
b1000000 7
b1000000 P
b1000000 s
b1000000 5
b1000000 O
b1000000 w
b111100 @
b111100 N
b111100 #"
b111100 &
b111100 6
b111100 _
b111100 t
b111100 u
b111100 !"
1)
#150000
0)
#155000
bx -
bx r
bx |
0!
bx (
bx C
bx T
bx o
bx p
bx E
bx I
bx m
b1000100 7
b1000100 P
b1000100 s
bx 8
bx Q
bx Z
bx e
bx j
bx %
bx 4
bx Y
bx d
bx }
bx ?
bx K
bx ^
bx h
bx 2
bx n
bx x
bx #
bx /
bx X
bx c
bx z
bx 1
bx H
bx S
bx y
bx "
bx .
bx W
bx b
bx {
bx >
bx J
bx ]
bx g
b1000100 5
b1000100 O
b1000100 w
b1000000 @
b1000000 N
b1000000 #"
bx '
bx <
bx [
bx a
bx i
b1000000 &
b1000000 6
b1000000 _
b1000000 t
b1000000 u
b1000000 !"
1)
